ntutrun/Builder.py
ntutrun/FindVisitor.py
ntutrun/GitDifferent.py
ntutrun/PythonResourceFile.py
ntutrun/ReportResultVisitor.py
ntutrun/ResourceBuilder.py
ntutrun/TestCase.py
ntutrun/TestCaseBuilder.py
ntutrun/__init__.py
ntutrun/init.py
ntutrun/main.py
ntutrun/testDataNode.py
ntutrun/tree.py
ntutrun-0.0.4.dist-info/LICENSE
ntutrun-0.0.4.dist-info/METADATA
ntutrun-0.0.4.dist-info/WHEEL
ntutrun-0.0.4.dist-info/top_level.txt
ntutrun-0.0.4.dist-info/RECORD
