Metadata-Version: 2.1
Name: ntutrun
Version: 0.0.4
Summary: A small example package
Home-page: https://github.com/pypa/sampleproject
Author: Example Author
Author-email: author@example.com
License: UNKNOWN
Platform: UNKNOWN
Classifier: Programming Language :: Python :: 3
Classifier: License :: OSI Approved :: MIT License
Classifier: Operating System :: OS Independent
Requires-Python: >=3.6
License-File: LICENSE
Requires-Dist: GitPython (>=3.0.8)
